tests/__init__.py
tests/test_lazy_property.py
xpyutils/__init__.py
xpyutils/singleton.py
xpyutils/property/__init__.py
xpyutils/property/base.py
xpyutils/property/lazy.py
xpyutils/property/presence_required.py
xpyutils-0.0.4.dist-info/METADATA
xpyutils-0.0.4.dist-info/WHEEL
xpyutils-0.0.4.dist-info/top_level.txt
xpyutils-0.0.4.dist-info/RECORD
