Metadata-Version: 2.1
Name: xpyutils
Version: 0.0.4
Summary: Ongoing project of extra Python utilities including implementations of lazy property, regular expression, ...
Author-email: Isaac Fei <isaac.omega.fei@gmail.com>
Project-URL: Homepage, https://github.com/Isaac-Fate/xpyutils
Requires-Python: >=3.0
